flask_access/__init__.py
flask_access/test_flask_access.py
flask_access-0.1.2.1.dist-info/LICENSE
flask_access-0.1.2.1.dist-info/METADATA
flask_access-0.1.2.1.dist-info/WHEEL
flask_access-0.1.2.1.dist-info/top_level.txt
flask_access-0.1.2.1.dist-info/RECORD
