Metadata-Version: 2.1
Name: flask-access
Version: 0.1.2.1
Summary: A Flask extension which limits access to views.
Home-page: UNKNOWN
License: UNKNOWN
Platform: UNKNOWN
Classifier: Programming Language :: Python :: 3
Classifier: License :: OSI Approved :: MIT License
Classifier: Operating System :: OS Independent
Classifier: Framework :: Flask
Classifier: Intended Audience :: Developers
Requires-Python: >=3
